[
    {"name": "Học viện Bưu chính Viễn thông", "address": "Km10 Nguyễn Trãi, Hà Đông, Hà Nội", "buses": "01, 02, 19, 21A, 22B, 27, 33, 105"},
    {"name": "Học viện An ninh Nhân dân", "address": "Km9 Nguyễn Trãi, Hà Đông, Hà Nội", "buses": "01, 02, 19, 21A, 22B, 27, 33, 39, 105"},
    {"name": "KCN Bắc Thăng Long", "address": "Xã Kim Chung, Đông Anh, Hà Nội", "buses": "07, 35B, 46, 53, 58, 60B, 61, 64, 93, 95, 109, 112, 115, 122, E10"},
    {"name": "Khu công nghệ cao Hòa Lạc (ĐH FPT)", "address": "Km29 Đại lộ Thăng Long, Thạch Thất, Hà Nội", "buses": "74, 88, 107"},
    {"name": "Làng lụa Vạn Phúc", "address": "Phường Vạn Phúc, Hà Đông, Hà Nội", "buses": "02, 19, 22C, 33, 89, 105"},
    {"name": "Rạp chiếu phim Quốc gia (NCC)", "address": "87 Láng Hạ, Đống Đa, Hà Nội", "buses": "09B, 12, 26, 30, 35A, 161"},
    {"name": "Chùa Hương (Bến Đục)", "address": "Xã Hương Sơn, Mỹ Đức, Hà Nội", "buses": "103A, 103B"},
    {"name": "Chợ Ninh Hiệp", "address": "Xã Ninh Hiệp, Gia Lâm, Hà Nội", "buses": "10, 54, 65"},
    {"name": "Chợ Long Biên", "address": "Phường Phúc Xá, Ba Đình, Hà Nội", "buses": "01, 04, 08A, 11, 14, 18, 22A, 23, 31, 34, 36, 47A, 50, 54, 65, 86, 98, 100, E11"},
    {"name": "Bến xe Nước Ngầm", "address": "Số 1 Ngọc Hồi, Hoàng Mai, Hà Nội", "buses": "03B, 16, 21B, 28, 37, 48, 60A, 60B, 104, 161"},
    {"name": "Sân vận động Hàng Đẫy", "address": "36 Trần Phú, Ba Đình, Hà Nội", "buses": "02, 18, 23, 25, 32, 34, 38, 41, 45, 159, E02, E07"},
    {"name": "Thiên đường Bảo Sơn", "address": "459 Đại lộ Thăng Long, An Khánh, Hoài Đức, Hà Nội", "buses": "19, 74, 87, 88, 107"},
    {"name": "Ga Gia Lâm", "address": "Phố Ngô Gia Khảm, Long Biên, Hà Nội", "buses": "01, 03A, 11, 15, 22A, 34"},
    {"name": "Bệnh viện K3 Tân Triều", "address": "Xã Tân Triều, Thanh Trì, Hà Nội", "buses": "22C, 37, 39, 62, 105, 106, 123, 158, E06"},
    {"name": "Học viện Kỹ thuật Quân sự", "address": "236 Hoàng Quốc Việt, Cầu Giấy, Hà Nội", "buses": "07, 14, 27, 28, 35A, 38, 45, 53, 60A"},
    {"name": "Đại học Thương mại", "address": "79 Hồ Tùng Mậu, Cầu Giấy, Hà Nội", "buses": "13, 20A, 26, 29, 32, 49, 56, 163"},
    {"name": "Đại học Công nghiệp Hà Nội (Nhổn)", "address": "Phố Nhổn, Nam Từ Liêm, Hà Nội", "buses": "20A, 20B, 29, 32, 57, 92, 117, 162, 163"},
    {"name": "Bệnh viện Trung ương Quân đội 108", "address": "1 Trần Hưng Đạo, Hai Bà Trưng, Hà Nội", "buses": "02, 03A, 04, 09A, 11, 18, 23, 34, 40, 43, 45, 49"},
    {"name": "Trung tâm chiếu phim Quốc gia", "address": "87 Láng Hạ, Đống Đa, Hà Nội", "buses": "09B, 12, 26, 30, 35A, 161"},
    {"name": "Times City (Cổng vòm)", "address": "458 Minh Khai, Hai Bà Trưng, Hà Nội", "buses": "19, 24, 45, 55A, E01, E04, E08"},
    {"name": "Học viện Tài chính", "address": "Học viện Tài chính, Đức Thắng, Bắc Từ Liêm, Hà Nội", "buses": "28, 31, 162"},
    {"name": "Đại học Văn hóa Hà Nội", "address": "418 La Thành, Đống Đa, Hà Nội", "buses": "02, 09B, 18, 23, 25, 28, 41, 49, 99, 142, 144, E07"},
    {"name": "Đại học Mỹ thuật Công nghiệp", "address": "360 La Thành, Đống Đa, Hà Nội", "buses": "02, 09B, 18, 23, 25, 28, 41, 49, 99, 142, 144, E07"},
    {"name": "Bệnh viện Thanh Nhàn", "address": "42 Thanh Nhàn, Hai Bà Trưng, Hà Nội", "buses": "04, 18, 26, 30, 42, 51, 159"},
    {"name": "Bệnh viện Da liễu Trung ương", "address": "15A Phương Mai, Đống Đa, Hà Nội", "buses": "18, 21A, 23, 26, 28, 47B, E03"},
    {"name": "Bệnh viện Tai Mũi Họng Trung ương", "address": "78 Giải Phóng, Đống Đa, Hà Nội", "buses": "03A, 08A, 18, 21A, 25, 28, 41"},
    {"name": "Bệnh viện Quân y 103", "address": "261 Phùng Hưng, Hà Đông, Hà Nội", "buses": "22C, 37, 39, 62, 103A, 105, 158"},
    {"name": "Công viên Thủ Lệ (Cầu Giấy)", "address": "Đường Bưởi, Ba Đình, Hà Nội", "buses": "07, 09A, 12, 25, 27, 28, 32, 34, 38, 161"},
    {"name": "Công viên Hòa Bình", "address": "Phạm Văn Đồng, Bắc Từ Liêm, Hà Nội", "buses": "07, 14, 25, 27, 28, 35A, 38, 45, 60A"},
    {"name": "Công viên Yên Sở", "address": "Yên Sở, Hoàng Mai, Hà Nội", "buses": "04, 08B, 21B, 48, 60A, 60B"},
    {"name": "Nhà hát Lớn Hà Nội", "address": "1 Tràng Tiền, Hoàn Kiếm, Hà Nội", "buses": "02, 04, 34, 40, 45, 49, 86"},
    {"name": "Cột cờ Hà Nội / Bảo tàng Lịch sử Quân sự", "address": "28A Điện Biên Phủ, Ba Đình, Hà Nội", "buses": "09A, 18, 23, 41, E07"},
    {"name": "Quảng trường Ba Đình", "address": "Hùng Vương, Ba Đình, Hà Nội", "buses": "09A, 22A, 33, 45, 50, E11"}
]